NiukeWangMingqiXiaozhaoBishiZhentiJingxuanChanpinYunyingYouxiCehuaPian20202021Fix1/README.md
NiukeWangMingqiXiaozhaoBishiZhentiJingxuanChanpinYunyingYouxiCehuaPian20202021Fix1/__init__.py
NiukeWangMingqiXiaozhaoBishiZhentiJingxuanChanpinYunyingYouxiCehuaPian20202021Fix1/__main__.py
NiukeWangMingqiXiaozhaoBishiZhentiJingxuanChanpinYunyingYouxiCehuaPian20202021Fix1/file.epub
NiukeWangMingqiXiaozhaoBishiZhentiJingxuanChanpinYunyingYouxiCehuaPian20202021Fix1/index.html
NiukeWangMingqiXiaozhaoBishiZhentiJingxuanChanpinYunyingYouxiCehuaPian20202021Fix1/css/__init__.py
NiukeWangMingqiXiaozhaoBishiZhentiJingxuanChanpinYunyingYouxiCehuaPian20202021Fix1/css/annotations.css
NiukeWangMingqiXiaozhaoBishiZhentiJingxuanChanpinYunyingYouxiCehuaPian20202021Fix1/css/main.css
NiukeWangMingqiXiaozhaoBishiZhentiJingxuanChanpinYunyingYouxiCehuaPian20202021Fix1/css/normalize.css
NiukeWangMingqiXiaozhaoBishiZhentiJingxuanChanpinYunyingYouxiCehuaPian20202021Fix1/css/popup.css
NiukeWangMingqiXiaozhaoBishiZhentiJingxuanChanpinYunyingYouxiCehuaPian20202021Fix1/font/__init__.py
NiukeWangMingqiXiaozhaoBishiZhentiJingxuanChanpinYunyingYouxiCehuaPian20202021Fix1/font/fontello.eot
NiukeWangMingqiXiaozhaoBishiZhentiJingxuanChanpinYunyingYouxiCehuaPian20202021Fix1/font/fontello.svg
NiukeWangMingqiXiaozhaoBishiZhentiJingxuanChanpinYunyingYouxiCehuaPian20202021Fix1/font/fontello.ttf
NiukeWangMingqiXiaozhaoBishiZhentiJingxuanChanpinYunyingYouxiCehuaPian20202021Fix1/font/fontello.woff
NiukeWangMingqiXiaozhaoBishiZhentiJingxuanChanpinYunyingYouxiCehuaPian20202021Fix1/img/__init__.py
NiukeWangMingqiXiaozhaoBishiZhentiJingxuanChanpinYunyingYouxiCehuaPian20202021Fix1/img/annotator-glyph-sprite.png
NiukeWangMingqiXiaozhaoBishiZhentiJingxuanChanpinYunyingYouxiCehuaPian20202021Fix1/img/annotator-icon-sprite.png
NiukeWangMingqiXiaozhaoBishiZhentiJingxuanChanpinYunyingYouxiCehuaPian20202021Fix1/img/apple-touch-icon.png
niuke_wang_mingqi_xiaozhao_bishi_zhenti_jingxuan_chanpin_yunying_youxi_cehua_pian_2020_2021_fix1-2025.3.24.1.dist-info/METADATA
niuke_wang_mingqi_xiaozhao_bishi_zhenti_jingxuan_chanpin_yunying_youxi_cehua_pian_2020_2021_fix1-2025.3.24.1.dist-info/WHEEL
niuke_wang_mingqi_xiaozhao_bishi_zhenti_jingxuan_chanpin_yunying_youxi_cehua_pian_2020_2021_fix1-2025.3.24.1.dist-info/entry_points.txt
niuke_wang_mingqi_xiaozhao_bishi_zhenti_jingxuan_chanpin_yunying_youxi_cehua_pian_2020_2021_fix1-2025.3.24.1.dist-info/top_level.txt
niuke_wang_mingqi_xiaozhao_bishi_zhenti_jingxuan_chanpin_yunying_youxi_cehua_pian_2020_2021_fix1-2025.3.24.1.dist-info/RECORD
